{
  "id": "ba21bee2-1ee5-47f5-8698-6193edeaf404",
  "prevId": "00000000-0000-0000-0000-000000000000",
  "version": "7",
  "dialect": "postgresql",
  "tables": {
    "public.embeddings": {
      "name": "embeddings",
      "schema": "",
      "columns": {
        "point_id": {
          "name": "point_id",
          "type": "serial",
          "primaryKey": true,
          "notNull": true
        },
        "embedding": {
          "name": "embedding",
          "type": "vector(384)",
          "primaryKey": false,
          "notNull": false
        }
      },
      "indexes": {},
      "foreignKeys": {
        "embeddings_point_id_points_id_fk": {
          "name": "embeddings_point_id_points_id_fk",
          "tableFrom": "embeddings",
          "tableTo": "points",
          "columnsFrom": [
            "point_id"
          ],
          "columnsTo": [
            "id"
          ],
          "onDelete": "cascade",
          "onUpdate": "no action"
        }
      },
      "compositePrimaryKeys": {},
      "uniqueConstraints": {}
    },
    "public.points": {
      "name": "points",
      "schema": "",
      "columns": {
        "id": {
          "name": "id",
          "type": "serial",
          "primaryKey": true,
          "notNull": true
        },
        "title": {
          "name": "title",
          "type": "text",
          "primaryKey": false,
          "notNull": true
        },
        "content": {
          "name": "content",
          "type": "text",
          "primaryKey": false,
          "notNull": true
        },
        "created_by": {
          "name": "created_by",
          "type": "varchar",
          "primaryKey": false,
          "notNull": true
        },
        "created_at": {
          "name": "created_at",
          "type": "timestamp",
          "primaryKey": false,
          "notNull": true,
          "default": "now()"
        }
      },
      "indexes": {},
      "foreignKeys": {
        "points_created_by_users_id_fk": {
          "name": "points_created_by_users_id_fk",
          "tableFrom": "points",
          "tableTo": "users",
          "columnsFrom": [
            "created_by"
          ],
          "columnsTo": [
            "id"
          ],
          "onDelete": "restrict",
          "onUpdate": "no action"
        }
      },
      "compositePrimaryKeys": {},
      "uniqueConstraints": {}
    },
    "public.users": {
      "name": "users",
      "schema": "",
      "columns": {
        "id": {
          "name": "id",
          "type": "varchar",
          "primaryKey": true,
          "notNull": true
        }
      },
      "indexes": {},
      "foreignKeys": {},
      "compositePrimaryKeys": {},
      "uniqueConstraints": {}
    }
  },
  "enums": {},
  "schemas": {},
  "sequences": {},
  "_meta": {
    "columns": {},
    "schemas": {},
    "tables": {}
  }
}